gridit/__init__.py
gridit/__main__.py
gridit/_version.py
gridit/array_from.py
gridit/cell.py
gridit/classmethods.py
gridit/cli.py
gridit/display.py
gridit/file.py
gridit/grid.py
gridit/gridpolyconv.py
gridit/logger.py
gridit/mfio.py
gridit/modflow.py
gridit/process.py
gridit/spatial.py
gridit-0.8.dist-info/METADATA
gridit-0.8.dist-info/WHEEL
gridit-0.8.dist-info/entry_points.txt
gridit-0.8.dist-info/licenses/LICENSE
gridit-0.8.dist-info/RECORD
