Metadata-Version: 2.4
Name: gridit
Version: 0.8
Summary: Spatial tools to translate raster or vector geometry data to regular grids
Project-URL: Repository, https://github.com/mwtoews/gridit
Author-email: Mike Taves <mwtoews@gmail.com>
License: BSD 3-Clause
License-File: LICENSE
Keywords: grid,rasterize,regular grid
Classifier: Intended Audience :: Science/Research
Classifier: License :: OSI Approved :: BSD License
Classifier: Programming Language :: Python :: 3 :: Only
Classifier: Topic :: Scientific/Engineering :: GIS
Requires-Python: >=3.10
Requires-Dist: numpy
Provides-Extra: dev
Requires-Dist: fiona; extra == 'dev'
Requires-Dist: flopy; extra == 'dev'
Requires-Dist: geopandas; extra == 'dev'
Requires-Dist: matplotlib; extra == 'dev'
Requires-Dist: netcdf4; extra == 'dev'
Requires-Dist: pre-commit; extra == 'dev'
Requires-Dist: pytest; extra == 'dev'
Requires-Dist: pytest-cov; extra == 'dev'
Requires-Dist: pytest-xdist; extra == 'dev'
Requires-Dist: rasterio; extra == 'dev'
Requires-Dist: ruff; extra == 'dev'
Requires-Dist: scipy; extra == 'dev'
Requires-Dist: shapely; extra == 'dev'
Requires-Dist: xarray; extra == 'dev'
Provides-Extra: optional
Requires-Dist: fiona; extra == 'optional'
Requires-Dist: flopy; extra == 'optional'
Requires-Dist: geopandas; extra == 'optional'
Requires-Dist: matplotlib; extra == 'optional'
Requires-Dist: netcdf4; extra == 'optional'
Requires-Dist: rasterio; extra == 'optional'
Requires-Dist: scipy; extra == 'optional'
Requires-Dist: shapely; extra == 'optional'
Requires-Dist: xarray; extra == 'optional'
Provides-Extra: test
Requires-Dist: pytest; extra == 'test'
Requires-Dist: pytest-cov; extra == 'test'
Requires-Dist: pytest-xdist; extra == 'test'
